hologres_mcp_server/__init__.py
hologres_mcp_server/server.py
hologres_mcp_server/settings.py
hologres_mcp_server/utils.py
hologres_mcp_server-0.1.9.dist-info/METADATA
hologres_mcp_server-0.1.9.dist-info/WHEEL
hologres_mcp_server-0.1.9.dist-info/entry_points.txt
hologres_mcp_server-0.1.9.dist-info/licenses/LICENSE
hologres_mcp_server-0.1.9.dist-info/RECORD
