Metadata-Version: 2.4
Name: hologres-mcp-server
Version: 0.1.9
Summary: A MCP Server for Hologres
Author-email: TimothyDing <ding_ye_timo@163.com>
License-File: LICENSE
Requires-Python: >=3.10
Requires-Dist: httpx>=0.28.1
Requires-Dist: mcp>=1.4.1
Requires-Dist: pglast>=7.5
Requires-Dist: psycopg-binary>=3.1.0
Requires-Dist: psycopg>=3.1.0
Requires-Dist: python-dotenv>=1.0.1
